{
  "$schema": "https://developer.microsoft.com/json-schemas/fabric/item/report/definition/visualContainer/1.0.0/schema.json",
  "name": "d3f77c567761eaa0b20d",
  "position": {
    "x": 435.71398379711167,
    "y": 80.794646002113424,
    "z": 3000,
    "width": 844.01549841493488,
    "height": 318.85029940119762,
    "tabOrder": 2000
  },
  "visual": {
    "visualType": "lineChart",
    "query": {
      "queryState": {
        "Category": {
          "projections": [
            {
              "field": {
                "HierarchyLevel": {
                  "Expression": {
                    "Hierarchy": {
                      "Expression": {
                        "PropertyVariationSource": {
                          "Expression": {
                            "SourceRef": {
                              "Entity": "UPI Data"
                            }
                          },
                          "Name": "Variation",
                          "Property": "Month"
                        }
                      },
                      "Hierarchy": "Date Hierarchy"
                    }
                  },
                  "Level": "Year"
                }
              },
              "queryRef": "UPI Data.Month.Variation.Date Hierarchy.Year",
              "nativeQueryRef": "Month Year",
              "active": true
            },
            {
              "field": {
                "HierarchyLevel": {
                  "Expression": {
                    "Hierarchy": {
                      "Expression": {
                        "PropertyVariationSource": {
                          "Expression": {
                            "SourceRef": {
                              "Entity": "UPI Data"
                            }
                          },
                          "Name": "Variation",
                          "Property": "Month"
                        }
                      },
                      "Hierarchy": "Date Hierarchy"
                    }
                  },
                  "Level": "Month"
                }
              },
              "queryRef": "UPI Data.Month.Variation.Date Hierarchy.Month",
              "nativeQueryRef": "Month Month",
              "active": true
            }
          ]
        },
        "Y": {
          "projections": [
            {
              "field": {
                "Aggregation": {
                  "Expression": {
                    "Column": {
                      "Expression": {
                        "SourceRef": {
                          "Entity": "UPI Data"
                        }
                      },
                      "Property": "Value (in Cr.)"
                    }
                  },
                  "Function": 0
                }
              },
              "queryRef": "Sum(Table1.Value (in Cr.))",
              "nativeQueryRef": "Sum of Value (in Cr.)",
              "displayName": "Value (in Cr.)"
            }
          ]
        }
      }
    },
    "objects": {
      "categoryAxis": [
        {
          "properties": {
            "bold": {
              "expr": {
                "Literal": {
                  "Value": "true"
                }
              }
            },
            "fontSize": {
              "expr": {
                "Literal": {
                  "Value": "10D"
                }
              }
            },
            "titleColor": {
              "solid": {
                "color": {
                  "expr": {
                    "Literal": {
                      "Value": "'#026256'"
                    }
                  }
                }
              }
            },
            "titleBold": {
              "expr": {
                "Literal": {
                  "Value": "true"
                }
              }
            }
          }
        }
      ],
      "valueAxis": [
        {
          "properties": {
            "bold": {
              "expr": {
                "Literal": {
                  "Value": "true"
                }
              }
            },
            "fontSize": {
              "expr": {
                "Literal": {
                  "Value": "10D"
                }
              }
            },
            "titleFontSize": {
              "expr": {
                "Literal": {
                  "Value": "12D"
                }
              }
            },
            "titleBold": {
              "expr": {
                "Literal": {
                  "Value": "true"
                }
              }
            },
            "titleColor": {
              "solid": {
                "color": {
                  "expr": {
                    "Literal": {
                      "Value": "'#026256'"
                    }
                  }
                }
              }
            },
            "titleItalic": {
              "expr": {
                "Literal": {
                  "Value": "false"
                }
              }
            },
            "titleUnderline": {
              "expr": {
                "Literal": {
                  "Value": "false"
                }
              }
            }
          }
        }
      ]
    },
    "visualContainerObjects": {
      "background": [
        {
          "properties": {
            "color": {
              "solid": {
                "color": {
                  "expr": {
                    "Literal": {
                      "Value": "'#ECF0EF'"
                    }
                  }
                }
              }
            },
            "show": {
              "expr": {
                "Literal": {
                  "Value": "true"
                }
              }
            }
          }
        }
      ],
      "title": [
        {
          "properties": {
            "fontColor": {
              "solid": {
                "color": {
                  "expr": {
                    "Literal": {
                      "Value": "'#026256'"
                    }
                  }
                }
              }
            },
            "bold": {
              "expr": {
                "Literal": {
                  "Value": "true"
                }
              }
            },
            "italic": {
              "expr": {
                "Literal": {
                  "Value": "true"
                }
              }
            },
            "underline": {
              "expr": {
                "Literal": {
                  "Value": "true"
                }
              }
            }
          }
        }
      ],
      "visualTooltip": [
        {
          "properties": {
            "background": {
              "solid": {
                "color": {
                  "expr": {
                    "ThemeDataColor": {
                      "ColorId": 2,
                      "Percent": -0.5
                    }
                  }
                }
              }
            }
          }
        }
      ]
    },
    "drillFilterOtherVisuals": true
  }
}